pyroll/marini_spreading.py
pyroll_marini_spreading-3.0.0.dist-info/METADATA
pyroll_marini_spreading-3.0.0.dist-info/WHEEL
pyroll_marini_spreading-3.0.0.dist-info/licenses/LICENSE
pyroll_marini_spreading-3.0.0.dist-info/RECORD
